unified_agent_interface/__init__.py
unified_agent_interface/app.py
unified_agent_interface/artifacts.py
unified_agent_interface/config.py
unified_agent_interface/instrumentation.py
unified_agent_interface/queue.py
unified_agent_interface/runtime.py
unified_agent_interface/utils.py
unified_agent_interface/api/__init__.py
unified_agent_interface/api/chat.py
unified_agent_interface/api/router.py
unified_agent_interface/api/run.py
unified_agent_interface/components/__init__.py
unified_agent_interface/components/agents/__init__.py
unified_agent_interface/components/agents/base.py
unified_agent_interface/components/agents/chat_configured.py
unified_agent_interface/components/agents/configured.py
unified_agent_interface/components/agents/run_base.py
unified_agent_interface/components/storage/__init__.py
unified_agent_interface/components/storage/base.py
unified_agent_interface/components/storage/memory.py
unified_agent_interface/frameworks/__init__.py
unified_agent_interface/frameworks/base.py
unified_agent_interface/frameworks/callable.py
unified_agent_interface/frameworks/crewai.py
unified_agent_interface/frameworks/langchain.py
unified_agent_interface/frameworks/utils.py
unified_agent_interface/models/__init__.py
unified_agent_interface/models/chat.py
unified_agent_interface/models/run.py
unified_agent_interface-0.1.1.dist-info/METADATA
unified_agent_interface-0.1.1.dist-info/WHEEL
unified_agent_interface-0.1.1.dist-info/entry_points.txt
unified_agent_interface-0.1.1.dist-info/licenses/LICENSE
unified_agent_interface-0.1.1.dist-info/RECORD
