Metadata-Version: 2.4
Name: unified-agent-interface
Version: 0.1.1
Summary: A unified interface for integrating various AI agents with a common protocol.
Author-email: chandralegend <irugalbandarachandra@gmail.com>
License-File: LICENSE
Requires-Python: >=3.10
Requires-Dist: fastapi>=0.116.1
Requires-Dist: httpx>=0.27.0
Requires-Dist: procrastinate>=3.5.1
Requires-Dist: python-dotenv>=1.1.1
Requires-Dist: tomli>=2.2.1
Requires-Dist: typer>=0.16.0
Requires-Dist: uvicorn>=0.35.0
